tablepyxl/__init__.py
tablepyxl/style.py
tablepyxl/tablepyxl.py
tablepyxl-0.6.1.dist-info/METADATA
tablepyxl-0.6.1.dist-info/WHEEL
tablepyxl-0.6.1.dist-info/top_level.txt
tablepyxl-0.6.1.dist-info/RECORD
